adder.t.v
// Adder testbench
`timescale 1 ns / 1 ps
`include "adder.v"

module testFullAdder();
    reg a, b, carryin;
    wire sum, carryout;

    // behavioralFullAdder adder (sum, carryout, a, b, carryin);
    structuralFullAdder adder (sum, carryout, a, b, carryin); // Swap after testing

    initial begin
    // Dump trace to a file. Open with gtkwave.
    $dumpfile("adder_waveform.vcd");
    $dumpvars();
    // Calling $dumpvars without arguments dumps all signals. This might be
    // too much as our circuits get bigger.

    $display("a b carryin | sum carryout | Exp Sum Exp Cout");
    a=0;b=0;carryin=0; #1000
    $display("%b %b   %b     |  %b     %b     |    0       0", a, b, carryin, sum, carryout);
    a=0;b=1;carryin=0; #1000
    $display("%b %b   %b     |  %b     %b     |    1       0", a, b, carryin, sum, carryout);
    a=1;b=0;carryin=0; #1000
    $display("%b %b   %b     |  %b     %b     |    1       0", a, b, carryin, sum, carryout);
    a=1;b=1;carryin=0; #1000
    $display("%b %b   %b     |  %b     %b     |    0       1", a, b, carryin, sum, carryout);
    a=0;b=0;carryin=1; #1000
    $display("%b %b   %b     |  %b     %b     |    1       0", a, b, carryin, sum, carryout);
    a=0;b=1;carryin=1; #1000
    $display("%b %b   %b     |  %b     %b     |    0       1", a, b, carryin, sum, carryout);
    a=1;b=0;carryin=1; #1000
    $display("%b %b   %b     |  %b     %b     |    0       1", a, b, carryin, sum, carryout);
    a=1;b=1;carryin=1; #1000
    $display("%b %b   %b     |  %b     %b     |    1       1", a, b, carryin, sum, carryout);
    
    $finish();	// End simulation
    end
endmodule

adder.v
// Adder circuit
// define gates with delays
`define AND and #50
`define OR or #50
`define XOR xor #50
`define NOT not #50

module behavioralFullAdder
(
    output sum, 
    output carryout,
    input a, 
    input b, 
    input carryin
);
    // Uses concatenation operator and built-in '+'
    assign {carryout, sum}=a+b+carryin;
endmodule

module structuralFullAdder
(
    output sum, 
    output carryout,
    input a, 
    input b, 
    input carryin
);

    wire xAorB;
    wire AandB;
    wire xAorBandCin;

    `XOR  xorgate(xAorB, a, b);   // OR gate produces AorB from A and B
    `XOR  xorgate(sum, xAorB, carryin);
    `AND  andgate(AandB, a, b);
    `AND  andgate(xAorBandCin, xAorB, carryin);
    `OR   orgate(carryout, AandB, xAorBandCin);
    
endmodule

adder_waveform.vcd
$date
	Thu Sep 20 16:57:43 2018
$end
$version
	Icarus Verilog
$end
$timescale
	1ps
$end
$scope module behavioralFullAdder $end
$var wire 1 ! a $end
$var wire 1 " b $end
$var wire 1 # carryin $end
$var wire 1 $ sum $end
$var wire 1 % carryout $end
$upscope $end
$scope module testFullAdder $end
$var wire 1 & sum $end
$var wire 1 ' carryout $end
$var reg 1 ( a $end
$var reg 1 ) b $end
$var reg 1 * carryin $end
$scope module adder $end
$var wire 1 + AandB $end
$var wire 1 ( a $end
$var wire 1 ) b $end
$var wire 1 * carryin $end
$var wire 1 ' carryout $end
$var wire 1 & sum $end
$var wire 1 , xAorB $end
$var wire 1 - xAorBandCin $end
$upscope $end
$upscope $end
$enddefinitions $end
#0
$dumpvars
x-
x,
x+
0*
0)
0(
x'
x&
x%
x$
z#
z"
z!
$end
#50000
0-
0+
0,
#100000
0'
0&
#1000000
1)
#1050000
1,
#1100000
1&
#2000000
0)
1(
#3000000
1)
#3050000
0,
1+
#3100000
0&
1'
#4000000
1*
0)
0(
#4050000
1&
0+
#4100000
0'
#5000000
1)
#5050000
1,
#5100000
0&
1-
#5150000
1'
#6000000
0)
1(
#7000000
1)
#7050000
0,
1+
#7100000
1&
0-
